LICENSE
README.md
setup.cfg
setup.py
TikTokLiveWrapper/__init__.py
TikTokLiveWrapper.egg-info/PKG-INFO
TikTokLiveWrapper.egg-info/SOURCES.txt
TikTokLiveWrapper.egg-info/dependency_links.txt
TikTokLiveWrapper.egg-info/requires.txt
TikTokLiveWrapper.egg-info/top_level.txt
TikTokLiveWrapper/client/__init__.py
TikTokLiveWrapper/client/client.py
TikTokLiveWrapper/client/errors.py
TikTokLiveWrapper/client/logger.py
TikTokLiveWrapper/client/web/__init__.py
TikTokLiveWrapper/client/web/web_base.py
TikTokLiveWrapper/client/web/web_client.py
TikTokLiveWrapper/client/web/web_presets.py
TikTokLiveWrapper/client/web/web_settings.py
TikTokLiveWrapper/client/web/routes/__init__.py
TikTokLiveWrapper/client/web/routes/download_video.py
TikTokLiveWrapper/client/web/routes/gift_list.py
TikTokLiveWrapper/client/web/routes/image_download.py
TikTokLiveWrapper/client/web/routes/is_live.py
TikTokLiveWrapper/client/web/routes/room_id_api.py
TikTokLiveWrapper/client/web/routes/room_id_live_html.py
TikTokLiveWrapper/client/web/routes/room_info.py
TikTokLiveWrapper/client/web/routes/sign_fetch.py
TikTokLiveWrapper/client/ws/__init__.py
TikTokLiveWrapper/client/ws/ws_client.py
TikTokLiveWrapper/client/ws/ws_connect.py
TikTokLiveWrapper/events/__init__.py
TikTokLiveWrapper/events/base_event.py
TikTokLiveWrapper/events/custom_events.py
TikTokLiveWrapper/events/proto_events.py
TikTokLiveWrapper/proto/__init__.py
TikTokLiveWrapper/proto/custom_proto.py
TikTokLiveWrapper/proto/proto_utils.py
TikTokLiveWrapper/proto/tiktok_proto.py