Metadata-Version: 2.1
Name: TikTokLiveWrapper
Version: 1.0.0
Summary: Unofficial Python API wrapper for TikTok Live
Author: Nico
Author-email: nicopizzolorusso.np@gmail.com
License: MIT
Keywords: tiktok,livestream,python,client,api,unofficial
Classifier: Development Status :: 4 - Beta
Classifier: Intended Audience :: Developers
Classifier: Topic :: Software Development :: Libraries
Classifier: License :: OSI Approved :: MIT License
Classifier: Natural Language :: English
Classifier: Programming Language :: Python :: 3.8
Classifier: Programming Language :: Python :: 3.9
Classifier: Programming Language :: Python :: 3.10
Classifier: Programming Language :: Python :: 3.11
License-File: LICENSE
Requires-Dist: httpx>=0.25.0
Requires-Dist: pyee>=9.0.4
Requires-Dist: ffmpy>=0.3.0
Requires-Dist: websockets_proxy==0.1.2
Requires-Dist: betterproto>=2.0.0b6
Requires-Dist: async-timeout>=4.0.3
Requires-Dist: mashumaro>=3.5
Requires-Dist: protobuf3-to-dict>=0.1.5
Requires-Dist: protobuf>=3.19.4
